olografos/__init__.py
olografos-1.0.2.dist-info/METADATA
olografos-1.0.2.dist-info/WHEEL
olografos-1.0.2.dist-info/top_level.txt
olografos-1.0.2.dist-info/RECORD
