Metadata-Version: 2.1
Name: olografos
Version: 1.0.2
Summary: A package to convert numbers to greek words
Home-page: https://github.com/imertz/olografos-py
Author: Yiannis Mertzanis
Author-email: imertz@protonmail.com
